{"Key":"刑","URL":"http://wyw.hwxnet.com/view/hwxE5hwx88hwx91.html","Pinyin":["xíng"],"BuShou":"刂","BuShouBiHua":"2","TotalBiHua":"6","BiShun":"横横撇竖竖竖","Desc":"xíng\n①\u003c名\u003e刑罚；刑法。《谏太宗十思疏》：“虽董之以严刑，振之以威怒。”\n②\u003c动\u003e判刑；处罚。《陈涉世家》：“皆刑其长吏，杀之以应陈涉。”\n③\u003c动\u003e杀。《与陈伯之书》：“并刑马作誓，传之子孙。”\n④\u003c名\u003e同“型”。模型；铸造器物的模子。《荀子·强国》：“刑范正，金锡美。”\n⑤\u003c名\u003e同“型”。法式；典范。《诗经·荡》：“虽无老成人，尚有典刑。”\n⑥\u003c动\u003e同“型”。作典范；作榜样。《齐桓晋文之事》：“刑于寡妻，至于兄弟，以御家邦。”\n【刑家】曾受刑罚的家族。","CY":["当刑而王","繁刑重赋","繁刑重敛","非刑逼拷","非刑吊拷","非刑拷打","讳兵畏刑","僭赏滥刑","决狱断刑","隆刑峻法","明刑弼教","明刑不戮","明正典刑","扑作教刑","省刑薄敛","威刑肃物","详刑慎罚","刑措不用","刑马作誓","刑期无刑"]}