{"Key":"创","URL":"http://wyw.hwxnet.com/view/hwxE5hwx88hwx9B.html","Pinyin":["chuàng","chuāng"],"BuShou":"刂","BuShouBiHua":"2","TotalBiHua":"6","BiShun":"撇捺折折竖竖","Desc":"chuāng\n\u003c名\u003e伤；伤口。《书博鸡者事》：“一步一呼，不呼则杖其背，尽创。”《荆轲刺秦王》：“秦王复击轲，被八创。”\nchuàng\n\u003c动\u003e开创，首创。《出师表》：“先帝创业未半而中道崩殂。”《复庵记》：“华下之人助之材，以创是庵而居之。”\n【创痏】1.创伤，疮伤。2.比喻民生疾苦，祸害。\n【创痍】也作“创夷”。1.创伤。班固《后汉书·袁谭传》：“放兵钞突，屠城杀吏，冤魂痛于幽冥，创被于草棘。”2.比喻人民遭受的战祸、疾苦。《史记·季布栾布列传》：“于今创未瘳，（樊）哙又面谀，欲摇动天下。”\n【创定】1.初定。2.制定，制作。\n【创艾】也作“创刈”。1.惩治,因受惩治而畏惧。《后汉书·南匈奴传》：“北单于创南兵，又畏丁令、鲜卑，遁逃远去。”2.以为鉴戒。《晋书·地理志》：“汉兴，创亡秦孤立而败，于是割裂封疆，立爵二等，功臣侯者百有馀邑。”","CY":["哀矜惩创","百孔千创","标新创异","别创一格","草创未就","创巨痛仍","创巨痛深","创剧痛深","创深痛巨","创家立业","创业垂统","创业维艰","创意造言","革命创制","艰苦创业","开基创业","痛自创艾","创钜痛仍","创钜痛深"]}