{"Key":"卒","URL":"http://wyw.hwxnet.com/view/hwxE5hwx8Dhwx92.html","Pinyin":["zú","cù"],"BuShou":"十","BuShouBiHua":"2","TotalBiHua":"8","BiShun":"捺横撇捺撇捺横竖","Desc":"zú\n①\u003c名\u003e步兵；士兵。《过秦论》：“率疲弊之卒，将数百之众，转而攻秦。”《郑伯克段于鄢》：“缮甲兵，具卒乘。”\n②\u003c名\u003e古代军队编制，一百人为一卒。《叔向贺贫》：“昔栾武子无一卒之田。”《谋攻》：“全卒为上，破卒次之。”\n③\u003c名\u003e差役；隶卒。《左忠毅公逸事》：“持五十金，涕泣谋于禁卒，卒感焉。”\n④\u003c动\u003e死。《董宣执法》：“年七十四，卒于官。”《赤壁之战》：“初，鲁肃闻刘表卒。”\n⑤\u003c动\u003e完成；完结。《孔雀东南飞》：“谓言无罪过，供养卒大恩。”《陈情表》：“庶刘侥幸保卒余年。”\n⑥\u003c副\u003e终于；最终。《廉颇蔺相如列传》：“卒相与欢，为刎颈之交。”《垓下之战》：“然今卒困于此，此天之亡我，非战之罪也。”\n【辨】兵，卒，士。上古时这三个字意义各不相同。“兵”一般指武器，也可泛指军队；“士”是战斗时在战车上的战士。\ncǜ\n\u003c副\u003e通“猝”。突然；仓猝。《荆轲刺秦王》：“卒惶不知所为。”《赤壁之战》：“五万兵难卒合。”","CY":["不忍卒读","残兵败卒","仓卒从事","仓卒应战","仓卒之际","仓卒主人","丢卒保车","儿童走卒","贩夫驺卒","贩夫走卒","躬先士卒","过河卒子","聊以卒岁","马前卒","轻卒锐兵","身先士卒","宿将旧卒","瓦合之卒","为德不卒","乌合之卒"]}