{"Key":"卷","URL":"http://wyw.hwxnet.com/view/hwxE5hwx8DhwxB7.html","Pinyin":["juăn","juàn","quán"],"BuShou":"厄","BuShouBiHua":"4","TotalBiHua":"8","BiShun":"捺撇横横撇捺折折","Desc":"juǎn\n①\u003c动\u003e把东西卷裹成圆筒形。《过秦论》：“有席卷天下，包举宇内，囊括四海之意。”\n②\u003c动\u003e翻卷；掀起；裹起。《念奴娇·赤壁怀古》：“乱石穿空，惊涛拍岸，卷起千堆雪。”《茅屋为秋风所破歌》：“八月秋高风怒号，卷我屋上三重茅。”\n③\u003c动\u003e席卷；全部盗取或侵吞。《葫芦僧判断葫芦案》：“他意欲卷了两家的银子逃去。”\njuàn\n①\u003c名\u003e书卷；书籍。《核舟记》：“鲁直左手执卷末，右手指卷。”\n②\u003c名\u003e整部书的一部分。《\u003c指南录\u003e后序》：“使北营，留北关外，为一卷。”\n③\u003c量\u003e表示文书、书籍的单位。《木兰辞》：“军书十二卷。”\n④\u003c名\u003e试卷；考卷。《左忠毅公逸事》：“呈卷，即而署第一。”","CY":["拔锅卷席","不忍释卷","电卷风驰","电卷星飞","读书破万卷","读万卷书，行万里路","风驰电卷","风驰云卷","风卷残雪","风卷残云","黄卷青灯","噤口卷舌","旌旗卷舒","卷地皮","卷甲倍道","卷甲韬戈","卷甲衔枚","卷铺盖","卷旗息鼓","卷土重来"]}