{"Key":"处","URL":"http://wyw.hwxnet.com/view/hwxE5hwxA4hwx84.html","Pinyin":["chŭ","chù"],"BuShou":"夂","BuShouBiHua":"3","TotalBiHua":"5","BiShun":"撇折捺竖捺","Desc":"chǔ\n①\u003c动\u003e停留，止息。《孙子·军事》：“是故卷甲而遁，日夜不处。”\n②\u003c动\u003e住，居住。《岳阳楼记》：“处江湖之远，则忧其君。”\n③\u003c动\u003e闲居，隐居。《孟子·齐人有一妻一妾》：“齐人有一妻一妾而处室者。”\n④\u003c动\u003e相处。《\u003c指南录\u003e后序》：“与贵酋处二十日，争曲直，屡当死。”\n⑤\u003c动\u003e处置，处理。《孔雀东南飞》：“处分适兄意，那得自任专！”《赤壁之战》：“愿将军量力而处之。”\nchù\n①\u003c名\u003e处所，地方。《垓下之战》：“令四面骑驰下，期山东为三处。”《过秦论》：“良将劲驽守要害之处。”《三峡》：“自三峡七百里中，两岸连山，略无阙处。”\n【处妇】居家之妇。\n【处妾】宫中的童女。\n【处士】1.有德才而隐居不愿作官的人。《荀子·非十二子》：“古之所谓处者，德盛者也，能静者也。”2.未做官的士人。《孟子·滕文公下》：“圣王不作，诸侯放恣，处横议，杨朱、墨翟之言盈天下。”3.星名，即少微。《晋书·天文志上》：“少微四星在太微西，士大夫之位也。一名处。”\n【处治】处方治病。\n【处子】1.处女。范晔《后汉书·张衡传》：“鸣鹤交颈，雎鸠相和。处怀春，精魂回移。”2.处士。《后汉书·逸民传序》：“自后帝德稍衰，邪嬖当朝，处耿介，羞与卿相等列。”","CY":["安常处顺","安身之处","安时处顺","安室利处","百无是处","抱法处势","不便之处","不遑宁处","不足之处","超然独处","巢居穴处","出处进退","出处殊途","出处语默","处安思危","处高临深","处静息迹","处士横议","处堂燕雀","处堂燕鹊"]}