{"Key":"富","URL":"http://wyw.hwxnet.com/view/hwxE5hwxAFhwx8C.html","Pinyin":["fù"],"BuShou":"宀","BuShouBiHua":"3","TotalBiHua":"12","BiShun":"捺捺折横竖折横竖折横竖横","Desc":"fù\n①\u003c形\u003e财产多；富裕；富足。《促织》：“独是成氏子以蠹贫，以促织富。”\n【又】\u003c形使动\u003e使……富足。《论积贮疏》：“可以为富安天下，而直为此廪廪也。”\n②\u003c形\u003e多；丰富。《塞翁失马》：“家富良马，其子好骑，堕而折其髀。”《黄生借书》：“有张氏藏书甚富。”\n③\u003c名\u003e财富；财产。《叔向贺贫》：“其富半公室，其家半三军。”\n【富年】指年轻少壮之时。\n【富岁】丰年。《孟子·告子上》：“富子弟多赖，凶岁子弟多暴。”","CY":["爱富嫌贫","安富恤贫","安富恤穷","安富尊荣","安国富民","百城之富","不汲汲于富贵","长命富贵","辞富居贫","打富济贫","大富大贵","妒富愧贫","多文为富","发财致富","发家致富","繁荣富强","丰富多采","丰富多彩","浮云富贵","富比陶卫"]}