{"Key":"度","URL":"http://wyw.hwxnet.com/view/hwxE5hwxBAhwxA6.html","Pinyin":["dù","duó","duò"],"BuShou":"广","BuShouBiHua":"3","TotalBiHua":"9","BiShun":"捺横撇横竖竖横折捺","Desc":"dù\n①\u003c名\u003e量长短的标准。也指按一定计量标准划分的单位。《汉书·律历志》：“度者，分、寸、尺、丈、引也。”（引：十丈。）《郑人买履》：“已得履，乃曰：‘吾忘持度。’”\n②\u003c名\u003e限度。《论积贮疏》：“生之有时，而用之无度，则物力必屈。”\n③\u003c名\u003e制度；法度。《答司马谏议书》：“谇法度而修之于朝廷，以授之于有司。”\n④\u003c名\u003e气度；度量。《荆轲刺秦王》：“群臣惊愕，卒起不意，尽失其度。”\n⑤\u003c名\u003e计划；打算。《答司马谏议书》：“盘庚不为怨者故改其度。”\n⑥\u003c动\u003e渡过；越过。《木兰诗》：“万里赴戎机，关山度若飞。”《凉州词》：“春风不度玉门关。”\n⑦\u003c量\u003e次；回。《江南逢李龟年》：“岐王宅里寻常见，崔九堂前几度闻。”\nduó\n①\u003c动\u003e量（长短）。《齐桓晋文之事》：“度，然后知长短。”《郑人买履》：“鸹自度其足而置其座。”\n②\u003c动\u003e计算；估计。《垓下之战》：“项主自度不得脱。”《廉颇蔺相如列传》：“相如度秦王虽斋，决负约不偿城。”\n③\u003c动\u003e砍伐。《左传·隐公十一年》：“山有木，工则度之。”","CY":["暗度金针","巴山度岭","不可揆度","长才广度","超度众生","称德度功","程门度雪","吃穿用度","初度之辰","揣时度力","穿荆度棘","春风一度","大度包容","大度豁达","大度汪洋","大明法度","当世才度","调度征求","度日如年","度日如岁"]}