{"Key":"排","URL":"http://wyw.hwxnet.com/view/hwxE6hwx8Ehwx92.html","Pinyin":["pái","păi"],"BuShou":"扌","BuShouBiHua":"3","TotalBiHua":"11","BiShun":"横竖横竖横横横竖横横横","Desc":"pái\n①\u003c动\u003e推；推开。诸葛亮《梁父吟》：“力能排南山。”\n②\u003c动\u003e排挤；排斥；排除。《后汉书·贾逵传》：“诸儒内怀不服，相与排之。”\n③\u003c动\u003e排除；消除；排解。《战国策·赵策三》：“为人排患释难难解难纷乱而无所取也。”\n④\u003c动\u003e排水；排泄。《孟子·滕文公》：“决汝汉，排淮泗，而注之江。”\n⑤\u003c动\u003e冲向；冲击。《\u003c黄花冈七十二烈士事略\u003e序》：“怨愤所，如怒涛排壑，不可遏抑。”\n⑥\u003c动\u003e排列；编排。白居易《春题湖上》：“松排山面千重翠，月点波心一颗珠。”\n⑦\u003c副\u003e挨个地；一一地。《高祖还乡》：“社长排门告示。”\n【排奡】矫健、刚劲貌。\n【排阖】推门。\n【排空】凌空。\n【排揎】数落；斥责。\n【排拶】挤压。\n【排訾】排斥诋毁。","CY":["击排冒没","解纷排难","力排众议","连山排海","论资排辈","排奡纵横","排兵布阵","排斥异己","排愁破涕","排除万难","排除异己","排患解纷","排糠障风","排难解纷","排沙简金","排沙见金","排山倒海","排山倒峡","排山压卵","排忧解难"]}