{"Key":"推","URL":"http://wyw.hwxnet.com/view/hwxE6hwx8EhwxA8.html","Pinyin":["tuī"],"BuShou":"扌","BuShouBiHua":"3","TotalBiHua":"11","BiShun":"横竖横撇竖捺横横横竖横","Desc":"tuī\n①\u003c动\u003e用手推。《陈州粜米》：“你可也被人推更不轻。”\n②\u003c动\u003e推移；移动。《谭嗣同》：“荣贼并非推心待慰帅者。”\n③\u003c动\u003e推求；推测。《察变》：“特据前事推未来，为变方长。”\n④\u003c动\u003e推广。《齐桓晋文之事》：“故推恩足以保四海。”\n⑤\u003c动\u003e推辞；推托。《林教头风雪山神庙》：“这番张教头没得推故了。”\n⑥\u003c动\u003e推荐；推举。《报任安书》：“教以慎于接物推贤进士为务。”\n⑦\u003c动\u003e推行；实行。《韩非子·五蠹》：“州部之吏操官兵，推公法，而求索奸人。”\n⑧\u003c动\u003e推崇；赞许。《墨池记》：“其亦欲推其事，以勉其学者邪。”\n⑨\u003c动\u003e假装。《长亭送别》：“猛然见了把头低，长吁气，推整素罗衣。”\n【推诚】以诚意待人。\n【推体】委身；以身相托。","CY":["半推半就","长江后浪推前浪","东推西阻","反复推敲","互相推托","互相推诿","讳败推过","校短推长","解骖推食","解衣推食","借水推船","叩源推委","六问三推","明推暗就","你推我让","旁推侧引","捧毂推轮","七推八阻","千推万阻","前挽后推"]}