{"Key":"更","URL":"http://wyw.hwxnet.com/view/hwxE6hwx9BhwxB4.html","Pinyin":["gèng","gēng"],"BuShou":"曰","BuShouBiHua":"4","TotalBiHua":"7","BiShun":"横竖折横横撇捺","Desc":"gēng\n①\u003c动\u003e改正；改变；更换。《\u003c论语\u003e十则》：“更也，人皆仰之。”《庖丁解牛》：“良庖岁更刀，割也；族庖月更刀折也。”《赤壁赋》：“客喜而笑，洗盏更酌。”\n②\u003c动\u003e经历；经过。《与吴质书》：“年三十余，在兵中十岁，所更非一。”《史记·大宛列传》：“因欲通使，道必更匈奴中。”\n③\u003c副\u003e交替；交互。《活板》：“更互用之，瞬息可就。”《左忠毅公逸事》：“使将更休。”\n④\u003c量\u003e古时夜间计时单位。一夜分五更，一更约二小时《孔雀东南飞》：“仰头相向鸣，夜夜达五更。”\ngèng\n①\u003c副\u003e另；另外。《荆轲刺秦王》：“丹不忍以已之私，而伤长者之意，愿足下更虑之。”《西门豹治邺》：“得更求好女，生日送之。”\n②\u003c副\u003e再；又。《石壕吏》：“室中更无人，惟有乳下孙。”王维《送元二使西安》：“劝君更尽一杯酒，西出阳关无故人。”\n③\u003c副\u003e重新。《琵琶行》：“莫辞更坐弹一曲，为君翻作琵琶行。”\n④\u003c副\u003e更加；愈加。《赤壁之战》：“今日拒之，事更不顺。”《促织》：“加以官贪吏虐，民日贴妇卖儿，更无休止。”\n⑤\u003c副\u003e还。《孔雀东南飞》：“仍更被驱遣，何言复来还。”\n⑥\u003c副\u003e岂，怎么。刘长卿《登润州万岁楼》：“更能谈笑解重围。”\n⑦\u003c连\u003e与；和。杨万里《春兴》：“不关春雨更春风。”\n⑧\u003c副\u003e却。《\u003c指南录\u003e后序》：“予更欲一觇北，归而求救国之策。”\n【更事】⒈阅历世事。⒉交替发生的事情；常事。","CY":["熬更守夜","百尺竿头，更进一步","半夜三更","除旧更新","涤故更新","改而更张","改容更貌","改弦更张","改姓更名","更长漏永","更长梦短","更唱迭和","更唱叠和","更阑人静","更令明号","更名改姓","更难仆数","更仆难尽","更仆难数","更仆难终"]}