{"Key":"茹","URL":"http://wyw.hwxnet.com/view/hwxE8hwx8ChwxB9.html","Pinyin":["rú","rù"],"BuShou":"艹","BuShouBiHua":"3","TotalBiHua":"9","BiShun":"横竖竖折撇横竖折横","Desc":"rú\n①\u003c动\u003e吃。《文选序》：“茹毛饮血之世。”\n【引】含。范成大《相州》：“茹痛含辛说乱华。”\n②\u003c名\u003e蔬菜的总称。枚乘《七发》：“白露之茹。”\n③\u003c形\u003e柔软。《韩非子·亡征》：“柔茹而寡断。”\n④\u003c动\u003e度量；估计。《诗经·小雅·六月》：“猃狁匪茹。”\n【又】猜测；猜想。《诗经·邶风·柏舟》：“我心匪鉴，不可以茹。”\n⑤\u003c形\u003e腐臭。《吕氏春秋·功名》：“以茹鱼去蝇，蝇愈至，不可禁。”","CY":["拔茅连茹","不吐不茹","餐风茹雪","饭粝茹蔬","饭糗茹草","攻苦茹酸","含悲茹痛","含冰茹檗","含荼茹毒","含辛茹苦","柔茹刚吐","柔茹寡断","茹古涵今","茹苦含辛","茹毛饮血","茹泣吞悲","茹柔吐刚","茹痛含辛","吐刚茹柔","衔悲茹恨"]}