{"Key":"近","URL":"http://wyw.hwxnet.com/view/hwxE8hwxBFhwx91.html","Pinyin":["jìn"],"BuShou":"辶","BuShouBiHua":"3","TotalBiHua":"7","BiShun":"撇撇横竖捺折捺","Desc":"jìn\n①\u003c形\u003e空间距离小，与“远”相对。《桃花源记》：“缘溪行，忘路之远近。”\n②\u003c形\u003e时间上距离短，与“久”“远”相对。《柳敬亭传》：“乃近年共称柳敬亭说书。”\n③\u003c动\u003e走近；靠近。《左忠毅公逸事》：“逆阉防伺甚严，虽家仆不得近。”\n④\u003c名\u003e近处；近旁。《察今》：“有道之士，贵以近知远。”\n⑤\u003c动\u003e亲近。《战国策·赵策》：“襄子必近幸子。”\n⑥\u003c形\u003e亲近的。《陈情表》：“外无期功强近之亲。”\n⑦\u003c动\u003e近似；接近；与……差异不大。《师说》：“位卑则足羞，官盛则近谀。”\n⑧\u003c形\u003e浅近；不够深厚或深奥。《答韦中立论师道书》：“仆道不笃，业甚浅近。”\n⑨\u003c副\u003e将近；差不多。《李愬雪夜入蔡州》：“闻愬军号令，应者近万人。”\n【近局】指邻居。","CY":["鞭辟近里","鞭约近里","不近道理","不近人情","道古稽今，言远合近","笃近举远","凡偶近器","贵远鄙近","贵远贱近","和蔼近人","祸近池鱼","急功近利","急功近名","近火先焦","近交远攻","近亲繁殖","近水楼台先得月","近乡情怯","近悦远来","近在眉睫"]}