{"Key":"交","URL":"http://wyw.hwxnet.com/view/hwxE4hwxBAhwxA4.html","Pinyin":["jiāo"],"BuShou":"亠","BuShouBiHua":"2","TotalBiHua":"6","BiShun":"捺横撇捺撇捺","Desc":"jiāo\n①\u003c动\u003e交叉；交错。《鸿门宴》：“交戟之士欲止不内。”\n②\u003c副\u003e交互；交相。《与朱元思书》：“疏条交映。”\n③\u003c动\u003e交换；互换。《左传·隐公三年》：“故周郑交质。”\n④\u003c动\u003e交接；交合。《促织》：“自昏达曙，目不交睫。”\n⑤\u003c动\u003e结交；交往。《赵威后问齐使》：“上不臣于王，下不治其家，中不索交诸侯。”\n⑥\u003c名\u003e交情；交谊。《廉颇蔺相如列传》：“卒相与欢，为刎刭之交。”\n⑦\u003c名\u003e同盟；盟约。《谋攻》：“故上兵伐谋，其次伐交。”《过秦论》：“合从缔交，相与为一。”\n⑧\u003c名\u003e时间或空间的交接处。《左传·僖公五年》：“其九月十月之交乎？”\n⑨\u003c动\u003e接受。《水浒传》：“一手交钱，一手交货。”\n⑩\u003c副\u003e全；都。《报刘一丈书》：“闻者亦心计交赞之。”\n⑾\u003c名\u003e交州的省称。《孔雀东南飞》：“杂彩三百匹，交广市鲑珍。”\n【交和】⒈互相和好，和合。⒉两军对垒。\n【交交】⒈象声词，鸟鸣声。⒉鸟飞来飞去的样子。⒊交加错杂的样子。\n【交通】⒈空间上的彼此通达。⒉交往；交游。⒊暗中勾结。⒋情感上的沟通交流。\n【交游】⒈交际；交往。⒉有交往的朋友。\n【交子】宋代发行的纸币。这是世界上发行最早的纸币。","CY":["哀喜交并","八拜为交","八拜之交","百端交集","百感交集","半面之交","杯觥交错","杯觥交杂","悲喜交并","悲喜交集","悲喜交加","悲喜交切","悲喜交至","不得开交","不可开交","布衣之交","持禄养交","杵臼交","杵臼之交","戴笠故交"]}