{"Key":"参","URL":"http://wyw.hwxnet.com/view/hwxE5hwx8Fhwx82.html","Pinyin":["cān","cēn","shēn"],"BuShou":"厶","BuShouBiHua":"2","TotalBiHua":"8","BiShun":"折捺横撇捺撇撇撇","Desc":"cān\n①\u003c动\u003e参与；参加。《柳敬停传》：“宁南以为相见之晚，使参机密。”《谭嗣同》：“与杨锐、林旭、刘光第同参预新政。”\n②\u003c动\u003e检验；检查。《劝学》：“君子博学而日参省乎己。”\n③\u003c动\u003e参考。《答韦中立论师道书》：“参之《国语》以博其趣；参之《离骚》以致其幽。”\n④\u003c动\u003e古代下级见上级叫参，见“参拜”。\n⑤\u003c动\u003e弹劾。《谭嗣同》：“即如前年胡景桂参劾慰帅一事。”\ncēn\n见“参差。”\nsān\n\u003c数\u003e三；三分。《左传·郑伯克段于鄢》：“大都不过参国之一。”（参国之一：国都的三分之一。国：国都。）\n【辨】三，参。“三”的意义比“参”广，“参”只用于“配合成三”或“三分”。该用“参”的地方有时可以用“三”，但该用“三”的地方不能用“参”。“三”在古代汉语中有时表示多数，“参”则无此用法。\nshēn\n①\u003c名\u003e星宿名。杜甫《赠卫八处士》：“人生不相见，动如参与商。”\n②药用植物名。《林黛玉进贾府》：“如今还是吃人参养荣丸。”\n【参拜】下属谒见长官。\n【参乘】即“骖乘”，坐在车子的右边担任警卫的人。司马迁《史记·樊郦滕灌列传》：“项羽目之，问为谁，张良曰：‘沛公参樊哙。’”\n【参天】高耸在天空中。\n【参赞】参谋；协助。《南史·王俭传》：“先是齐高帝为相，欲引时贤参大业。”\n【参佐】僚属，部下。《三国志·魏书·王基传》：“基上疏固让，归功参。”\n【参差】长短、高低不齐和纷繁不一的样子。《小石潭记》：“青树翠蔓，蒙络摇缀，参披拂。”《柳毅传》：“明珰满身，绡縠参。”","CY":["笔参造化","参前倚衡","参透机关","参差不齐","参差不一","参差错落","参错重出","晨参暮礼","晨参暮省","错落参差","得失参半","动如参商","斗转参横","斗转参斜","古木参天","毁誉参半","扪参历井","暮礼晨参","日月参辰","参参伍伍"]}