{"Key":"完","URL":"http://wyw.hwxnet.com/view/hwxE5hwxAEhwx8C.html","Pinyin":["wán"],"BuShou":"宀","BuShouBiHua":"3","TotalBiHua":"7","BiShun":"捺捺折横横撇折","Desc":"wán\n①\u003c形\u003e完整；完好。《石壕吏》：“有孙母未去，出入无完裙。”《廉颇蔺相如列传》：“城不入，臣请完璧归赵。”\n②\u003c动\u003e保全。\n【又】〈形使动〉使……完好无缺。《六国论》：“盖失强援，不能独完。”\n③\u003c动\u003e修缮；修补。《孟子·万章》：“父母使舜完廪。”\n④\u003c名\u003e古代的一种较轻的刑罚，剃去犯人的颊毛和鬃毛。《汉书·刑法志》：“完者使守积。”\n【完聚】⒈修筑城郭，积聚粮食。⒉团聚。\n【完行】⒈使操行完美。⒉完美的操行。\n【完具】完全；完备。","CY":["大璞不完","大事完毕","短褐不完","覆巢无完卵","功完行满","褐衣不完","肌无完肤","金无足赤，人无完人","鹿裘不完","没完没了","破巢完卵","身无完肤","神完气足","神完守固","裋褐不完","体无完肤","体无完皮","完璧归赵","完好无缺","完美无疵"]}