{"Key":"恶","URL":"http://wyw.hwxnet.com/view/hwxE6hwx81hwxB6.html","Pinyin":["è","ĕ","wù","wū"],"BuShou":"心","BuShouBiHua":"4","TotalBiHua":"10","BiShun":"横竖竖捺撇横捺折捺捺","Desc":"è\n①\u003c形\u003e罪恶；邪恶。与“善”相对。《谏太宗十思疏》：“惧谗邪则思正身以黜恶。”《\u003c指南录\u003e后序》：“不幸吕师孟构恶于前，贾余庆献谄于后。”\n②\u003c形\u003e丑；丑陋。与“美”相对。《釆草药》：“未花时釆，则根色鲜泽；花过而釆，则根色黯恶。”\n③\u003c形\u003e坏；不好。《论积贮疏》：“岁恶不人，请卖爵子。”《廉颇蔺相如列传》：“今君与廉颇同列，廉君宣恶言，而君畏匿之。”\n④\u003c形\u003e污秽。《五蠹》：“腥臊恶臭而伤害腹胃”《报刘一丈书》：“立厩中仆马之间，恶气袭衣裾”\n⑤\u003c形\u003e险恶；凶险。《\u003c指南录\u003e后序》：“而境界危恶，层见错出，非人世所堪。”\nwù\n①\u003c动\u003e憎恶；讨厌；不喜欢。《鱼我所欲也》：“死亦我所恶，所恶有甚于死者，故患有所不避也。”\n②\u003c名\u003e耻辱；羞辱。《史记·平原君列传》：“此百世之怨，而赵之所羞，而王弗知恶焉。”\n③\u003c动\u003e嫉妒。《赤壁之战》：“表恶其能而不能用也。”\nwū\n①\u003c代\u003e哪里；怎么。《齐桓晋文之事》：“以小易大，彼恶知之？”《满井游记》：“余之游将从此始，恶能无记？。”\n②\u003c叹\u003e相当于“啊”、“唉”。《孟子·公孙丑上》：“恶！是何言也。”","CY":["爱生恶死","爱则加诸膝，恶则坠诸渊","爱之欲其生，恶之欲其死","褒善贬恶","褒贤遏恶","敝绨恶粟","蔽美扬恶","播恶遗臭","不恶而严","不念旧恶","采善贬恶","剗恶锄奸","铲恶锄奸","长恶不悛","长恶靡悛","惩恶劝善","丑类恶物","除恶务本","除恶务尽","除邪惩恶"]}