{"Key":"治","URL":"http://wyw.hwxnet.com/view/hwxE6hwxB2hwxBB.html","Pinyin":["zhì"],"BuShou":"氵","BuShouBiHua":"3","TotalBiHua":"8","BiShun":"捺捺横折捺竖折横","Desc":"zhì\n①\u003c动\u003e治理。《论积贮疏》：“民不足而可治者，自下及今未之尝闻。”\n②\u003c动\u003e惩处。《出师表》：“不效则治臣之罪。”\n③\u003c动\u003e医治。《扁鹊见蔡桓公》：“君有疾在腠理，不治将恐深。”\n④\u003c动\u003e建造。《西门豹治邺》：“为治斋宫河上。”\n⑤\u003c动\u003e整理；备办。《冯谖客孟尝君》：“于是约车治装，载券契而行。”\n⑥\u003c动\u003e训练。《左忠毅公逸事》：“史公治兵，往来桐城。”\n⑦\u003c动\u003e对付；抵御。《赤壁之战》：“同心一意，共治曹操。”\n⑧\u003c动\u003e处理。《苏武传》：“单于使卫律治其事。”\n⑨\u003c动\u003e讲求；研究。《齐桓晋文之事》：“此惟救死而恐不赡，奚暇治礼义哉。”\n⑩\u003c名\u003e地方政府所在地。《过小孤山大孤山》：“州治德化县，即唐之浔阳县。”\n⑾\u003c形\u003e治理得好；太平。《屈原列传》：“明于治乱，娴于辞令。”\n【治具】⒈置办酒食。⒉治国措施。\n【治剧】处理难办的事情。\n【治世】治理得好的时代，太平盛世。\n【治严】\n【治装】均为整理行装。","CY":["安邦治国","百治百效","半部论语治天下","拨乱反治","拨乱为治","拨乱兴治","不治生产","不治之症","长治久安","垂拱而治","大禹治水","分而治之","即以其人之道，还治其人之身","诘戎治兵","结绳而治","久安长治","举要治繁","厉精求治","厉精图治","厉精为治"]}