{"Key":"献","URL":"http://wyw.hwxnet.com/view/hwxE7hwx8ChwxAE.html","Pinyin":["xiàn"],"BuShou":"犬","BuShouBiHua":"4","TotalBiHua":"13","BiShun":"横竖竖折捺撇横横竖横撇捺捺","Desc":"xiàn\n①\u003c动\u003e献祭。《仪礼·聘礼》：“荐脯醢，三献。”\n②\u003c动\u003e奉献；进献。《捕蛇者说》：“谨食之，时而献焉。”\n③\u003c动\u003e提出。《愚公移山》：“其妻献疑。”\n④\u003c动\u003e表现；呈现。柳宗元《钴鉧潭西小丘记》：“由其中以望，则山之高、云之浮、鸟兽之游，举熙熙然回巧献技。”\n【献芹】上书建议自谦意见不足取，或以物赠给，谦言礼品微薄，称献芹或芹献。","CY":["白璧三献","承欢献媚","出谋献策","打勤献趣","当场献丑","多嘴献浅","飞觥献斝","负暄之献","借花献佛","美芹之献","田父献曝","献酬交错","献计献策","献可替不","献可替否","献曝之忱","献替可否","野人献曝","野人献芹","野人献日"]}