{"Key":"类","URL":"http://wyw.hwxnet.com/view/hwxE7hwxB1hwxBB.html","Pinyin":["lèi"],"BuShou":"米","BuShouBiHua":"6","TotalBiHua":"9","BiShun":"捺撇横竖撇捺横撇捺","Desc":"lèi\n①\u003c名\u003e种类；类别。《齐桓晋文之事》：“王之不王，是折枝之类也。”\n②\u003c动\u003e类推；推论。《公输》：“义不杀少而杀众，不可谓知类。”\n③\u003c动\u003e类似；像。《与吴质书》：“志意何时复类昔日。”《项脊轩志》：“何竟日默默在此，大类女郎也?”\n④\u003c名\u003e事例；事物。《屈原列传》：“举类迩而见义远。”\n⑤\u003c副\u003e大抵；大致。《训俭示康》：“走卒类士服，农夫蹑丝履。”\n⑥\u003c名\u003e典范；榜样。《怀沙》：“明告君子，吾将以为类兮。”","CY":["拔丛出类","拔萃出类","拔类超群","拔群出类","比类从事","比物丑类","比物连类","别类分门","不伦不类","超类绝伦","超群拔类","超群轶类","充类至尽","丑类恶物","出乎其类，拔乎其萃","出类拔萃","出类拔群","出类超群","触类而长","触类而通"]}