{"Key":"钧","URL":"http://wyw.hwxnet.com/view/hwxE9hwx92hwxA7.html","Pinyin":["jūn"],"BuShou":"钅","BuShouBiHua":"5","TotalBiHua":"9","BiShun":"撇横横横折撇折捺横","Desc":"jūn\n①\u003c量\u003e古代重量单位，三十斤为一钧。《齐桓晋文之事》：“吾力足以举百钧，而不足举一羽。”\n②\u003c名\u003e制作陶器的转轮。桓宽《盐铁论·遵道》：“转若陶钧。”\n③\u003c形\u003e通“均”，同样的，对等的。《史记·平准书》：“自天子不能具钧驷。”\n【又】平均地；均匀地。《荀子·议兵》：“明道而钧分之。”\n④\u003c形\u003e犹“大”，用于修饰跟尊长或上级有关的事物，以表示尊敬。《长生殿》：“请问王爷传集某等，不知有何钧令。”","CY":["秉钧持轴","秉钧当轴","秉轴持钧","蝉翼为重，千钧为轻","发引千钧","广乐钧天","钧天广乐","钧天之乐","雷霆万钧","力敌千钧","力钧势敌","千钧一发","千钧重负","权钧力齐","势钧力敌","一发千钧","一字千钧","宗匠陶钧"]}