{"Key":"风","URL":"http://wyw.hwxnet.com/view/hwxE9hwxA3hwx8E.html","Pinyin":["fēng"],"BuShou":"风","BuShouBiHua":"4","TotalBiHua":"4","BiShun":"撇折撇捺","Desc":"fēng\n①\u003c名\u003e空气流动的自然现象。\n②\u003c名\u003e教化;感化。《战国策·秦策》：“山东之国,从风而服。”\n③\u003c名\u003e风俗;风气。《捕蛇者说》：“以俟观人风者得焉。”陆游《游西山村》：“衣冠简朴古风存。”\n④\u003c名\u003e作风；风度。《孟子·万章》：“故闻柳下惠之风声，鄙乎宽，薄乎敦。”\n⑤\u003c名\u003e民歌；民谣。如《诗经》中的十五国风。\n⑥\u003c名\u003e风声；消息。《儒林外史》：“才晓得是门子透风。”\n⑦\u003c名\u003e景象；景色。如“风景”。\n⑧\u003c动\u003e吹风；乘凉。《子路曾皙冉有公西华侍坐》：“浴乎沂，风乎舞雩。”\n⑨\u003c名\u003e某些疾病的名称，如麻风。\nfàng﹤动﹥通“讽”，用含蓄的话暗示或劝告。《汉书·蚡田传》：“乃微言太后风上。”","CY":["挨风缉缝","捱风缉缝","八方风雨","八面驶风","八面威风","霸王风月","败化伤风","败俗伤风","伴风搭雨","饱经风霜","饱经风雨","暴风疾雨","暴风骤雨","北风之恋","笔底春风","毕雨箕风","弊绝风清","避风港","抃风舞润","抃风儛润"]}